Metadata-Version: 2.1
Name: cprofiler-manager-wrapper
Version: 0.0.6
Summary: simple_profiler
Home-page: https://github.com/Rwwwrl/SimpleProfiler
Author: Alexey Sosov
Author-email: lesh.solowiew@yandex.ru
License: BSD-3-Clause
Platform: UNKNOWN
Classifier: Environment :: Web Environment
Classifier: Intended Audience :: Developers
Classifier: License :: OSI Approved :: BSD License
Classifier: Operating System :: OS Independent
Classifier: Programming Language :: Python :: 3.8
Classifier: Programming Language :: Python :: 3.9
Classifier: Programming Language :: Python :: 3.10
Requires-Python: >=3.8
